{
  "publication": {
    "reference_number": "1812",
    "publication_type": "article",
    "title": "FREHER M. Rerum Germanicarum Scriptores aliquot insignes : Qui gesta sub Regibus & Imperatoribus Teutonicis [..] perpetua ferè serie, suis quique seculis, litteris mandata posteritati reliquerunt. Tomus [..] ; ex bibliotheca Marquardi Freheri [..] olim editus, nunc denuo recognitus, additis scriptoribus aliis antea ineditis; cum glossario, locis aliorum auctorum parallelis, notis ac indice rerum & verborum copiosissimo. Editio tertia, reliquis locupletior et emendatior. Curante Burcardo Gotthelffio Struvio, 3 tomes, Strasbourg, 1717, p.368-371,DU CHESNE A. Historiae Francorvm Scriptores Coaetanei: Quorum plurimi nunc primùm ex variis Codicibus Mss. in lucem prodeunt ; alij verò auctiores & emendatiores ; Cvm Epistolis Regvm, Reginarvm, Pontificvm, Ducum, Comitum, Abbatum, & aliis veteribus Rerum Francicarum Monumentis, Lutetiae Parisiorum, 5 vol, 1636-1649",
    "auteurs": [
      "FREHER M. Rerum Germanicarum Scriptores aliquot insignes"
    ],
    "place_of_publication": null,
    "publisher": null,
    "publication_dates": "1636-1649",
    "volume": "5 vol",
    "tome": null,
    "pages": "368-371",
    "series": null,
    "journal_title": "lucem prodeunt ; alij verò auctiores & emendatiores ; Cvm Epistolis Regvm",
    "journal_volume": null,
    "journal_issue": null,
    "container_title": null,
    "container_editors": []
  },
  "content": {
    "main_institution": null,
    "mentioned_place": null,
    "region": null,
    "country": null,
    "institution_type": null,
    "religious_order": null,
    "temporal_coverage": null,
    "document_type": null
  },
  "remarks": null
}